CHANGELOG.md
LICENSE.txt
MANIFEST.in
README.md
requirements.txt
setup.py
blend_modes/__init__.py
blend_modes/blending_functions.py
blend_modes/type_checks.py
blend_modes.egg-info/PKG-INFO
blend_modes.egg-info/SOURCES.txt
blend_modes.egg-info/dependency_links.txt
blend_modes.egg-info/requires.txt
blend_modes.egg-info/top_level.txt
docs/.DS_Store
docs/Makefile
docs/README.rst
docs/conf.py
docs/index.rst
docs/make_readme_pandoc.py
docs/reference.rst
docs/visual_examples.rst