Metadata-Version: 1.1
Name: blend_modes
Version: 2.1.0
Summary: Image processing blend modes
Home-page: https://github.com/flrs/blend_modes
Author: Florian Roscheck
Author-email: florian.ros.check+blendmodes@gmail.com
License: MIT
Keywords: image processing blend modes
Platform: UNKNOWN
Classifier: Development Status :: 5 - Production/Stable
Classifier: Intended Audience :: Developers
Classifier: Topic :: Multimedia :: Graphics :: Graphics Conversion
Classifier: License :: OSI Approved :: MIT License
Classifier: Programming Language :: Python :: 3.5
